.gitignore
CHANGES.txt
LICENSE.txt
MANIFEST.in
README.md
manual.pdf
setup.cfg
setup.py
bin/BCC-interstitial.yaml
bin/CLdiffuser.py
bin/FCC-interstitial.yaml
bin/HCP-interstitial.T
bin/HCP-interstitial.yaml
bin/OctaTetra-interstitial.py
bin/fivefreq.dat
bin/fivefreq.py
docs/Makefile
docs/source/CrystalStars.rst
docs/source/GFcalc.rst
docs/source/OnsagerCalc.rst
docs/source/PowerExpansion.rst
docs/source/automator.rst
docs/source/conf.py
docs/source/crystal.rst
docs/source/includeme.rst
docs/source/index.rst
docs/source/notebooks.rst
docs/source/supercell.rst
docs/source/examples/Fe-C.ipynb
docs/source/examples/GF-convergence.ipynb
docs/source/examples/Garnet.ipynb
docs/source/examples/LargeOmega2.ipynb
docs/source/examples/Tracer-correlation.ipynb
examples/FCC-Co-O.ipynb
examples/Fe-C.ipynb
examples/GF-RBC.ipynb
examples/GF-convergence.ipynb
examples/Garnet.ipynb
examples/HCPtracer.ipynb
examples/KMCfromJumpNetwork.ipynb
examples/LargeOmega2.ipynb
examples/NiSi.ipynb
examples/Random-alloy.ipynb
examples/Tracer-correlation.ipynb
onsager/GFcalc.py
onsager/OnsagerCalc.py
onsager/PowerExpansion.py
onsager/Vasp.pm
onsager/__init__.py
onsager/automator.py
onsager/cluster.py
onsager/crystal.py
onsager/crystalStars.py
onsager/nebmake.pl
onsager/supercell.py
onsager/trans.pl
onsager.egg-info/PKG-INFO
onsager.egg-info/SOURCES.txt
onsager.egg-info/dependency_links.txt
onsager.egg-info/requires.txt
onsager.egg-info/top_level.txt
test/__init__.py
test/test_GFcalc.py
test/test_HDF5.py
test/test_OnsagerCalc.py
test/test_PowerExpansion.py
test/test_cluster.py
test/test_crystal.py
test/test_crystalStars.py
test/test_supercell.py
test/tests.py