Metadata-Version: 2.1
Name: onsager
Version: 1.4
Summary: A package to compute Onsager coefficients for vacancy-mediated diffusion and interstitial elastodiffusion tensors
Home-page: https://github.com/DallasTrinkle/onsager
Download-URL: https://github.com/DallasTrinkle/onsager/tarball/v1.3.3
Author: Dallas R. Trinkle
Author-email: dtrinkle@illinois.edu
License: MIT
Keywords: diffusion,elastodiffusion,mass transport,Onsager coefficients,transport coefficieints
Classifier: Development Status :: 4 - Beta
Classifier: Intended Audience :: Science/Research
Classifier: Topic :: Scientific/Engineering :: Physics
Classifier: License :: OSI Approved :: MIT License
Classifier: Programming Language :: Python :: 3
Classifier: Programming Language :: Python :: 3.8
Classifier: Programming Language :: Python :: 3.9
Classifier: Programming Language :: Python :: 3.10
Classifier: Programming Language :: Python :: 3.11
License-File: LICENSE.txt
Requires-Dist: numpy
Requires-Dist: scipy
Requires-Dist: pyyaml
Requires-Dist: h5py
Requires-Dist: numba
